{
    "model": "Triple2vec",
    "config_id":"default",
    "root_dir":"../",
    "dataset": "dunnhumby",
    "data_split":"temporal",
    "data_split_comment":"temporal: temporal split, leave_one_out: leave one basket out split",
    "temp_train":0,
    "temp_train_comment":"0 for using normal training, 1 for using temporal training",
    "percent": 1,
    "n_sample": 1000000,
    "n_sample_comment":"options are: 1m-10m",
    "metrics": ["ndcg_at_k", "precision_at_k", "recall_at_k", "map_at_k"],
    "validate_metric": "ndcg_at_k@10",
    "emb_dim": 128,
    "emb_dim_comment":"options are: 128,256,512",
    "n_neg": 5,
    "batch_size": 256,
    "device": "gpu",
    "optimizer": "adam",
    "lr": 0.0005,
    "l2_regularization": 0.01,
    "max_epoch": 120,
    "result_file": "result.csv",
    "log_dir": "logs/",
    "result_dir": "results/",
    "checkpoint_dir": "checkpoints/",
    "dataset_dir": "datasets/",
    "sample_dir": "samples/",
    "run_dir": "runs/"
}